pyKoalaUtils/KoalaUtils.py
pyKoalaUtils/__init__.py
pyKoalaUtils/binkoala.py
pyKoalaUtils-0.0.4.dist-info/LICENSE
pyKoalaUtils-0.0.4.dist-info/METADATA
pyKoalaUtils-0.0.4.dist-info/WHEEL
pyKoalaUtils-0.0.4.dist-info/top_level.txt
pyKoalaUtils-0.0.4.dist-info/RECORD
